CHANGELOG.md
README.md
mitol/__init__.py
mitol/google_sheets_refunds/__init__.py
mitol/google_sheets_refunds/admin.py
mitol/google_sheets_refunds/api.py
mitol/google_sheets_refunds/apps.py
mitol/google_sheets_refunds/constants.py
mitol/google_sheets_refunds/hooks.py
mitol/google_sheets_refunds/models.py
mitol/google_sheets_refunds/py.typed
mitol/google_sheets_refunds/utils.py
mitol/google_sheets_refunds/management/commands/process_refund_requests.py
mitol/google_sheets_refunds/migrations/0001_initial.py
mitol/google_sheets_refunds/migrations/0002_alter_refundrequest_id_make_bigauto.py
mitol/google_sheets_refunds/migrations/__init__.py
mitol/google_sheets_refunds/settings/google_sheets_refunds.py
mitol_django_google_sheets_refunds-2025.6.13.dist-info/METADATA
mitol_django_google_sheets_refunds-2025.6.13.dist-info/WHEEL
mitol_django_google_sheets_refunds-2025.6.13.dist-info/RECORD
