Metadata-Version: 2.4
Name: mitol-django-google-sheets-refunds
Version: 2025.6.13
Summary: Library to handle Refund requests using Google Sheets integrations in Django
License-Expression: BSD-3-Clause
Requires-Python: >=3.10
Requires-Dist: django-stubs>=1.13.1
Requires-Dist: django>=3.0
Requires-Dist: mitol-django-common
Requires-Dist: mitol-django-google-sheets
Requires-Dist: pluggy>0.13.1
